quantplay/__init__.py
quantplay/py.typed
quantplay/broker/__init__.py
quantplay/broker/aliceblue.py
quantplay/broker/angelone.py
quantplay/broker/broker_factory.py
quantplay/broker/dhan.py
quantplay/broker/five_paisa.py
quantplay/broker/flattrade.py
quantplay/broker/icici_direct.py
quantplay/broker/iifl_xts.py
quantplay/broker/jainam_xts.py
quantplay/broker/kite_utils.py
quantplay/broker/kotak.py
quantplay/broker/kotak_v2.py
quantplay/broker/motilal.py
quantplay/broker/noren.py
quantplay/broker/shoonya.py
quantplay/broker/upstox.py
quantplay/broker/xts.py
quantplay/broker/zerodha.py
quantplay/broker/angelone_utils/__init__.py
quantplay/broker/angelone_utils/angeloneWS.py
quantplay/broker/auto_login/__init__.py
quantplay/broker/auto_login/aliceblue.py
quantplay/broker/breeze/__init__.py
quantplay/broker/breeze/breeze_utils.py
quantplay/broker/finvasia_utils/__init__.py
quantplay/broker/finvasia_utils/fa_noren.py
quantplay/broker/ft_utils/__init__.py
quantplay/broker/ft_utils/flattrade_utils.py
quantplay/broker/ft_utils/ft_noren.py
quantplay/broker/generics/__init__.py
quantplay/broker/generics/broker.py
quantplay/broker/kotak_utils/__init__.py
quantplay/broker/kotak_utils/kotak_ws.py
quantplay/broker/kotak_utils/kotak_ws_lib.py
quantplay/broker/uplink/__init__.py
quantplay/broker/uplink/uplink_utils.py
quantplay/broker/xts_utils/Connect.py
quantplay/broker/xts_utils/Exception.py
quantplay/broker/xts_utils/InteractiveSocketClient.py
quantplay/broker/xts_utils/__init__.py
quantplay/broker/xts_utils_v2/ConnectV2.py
quantplay/broker/xts_utils_v2/InteractiveSocketClientV2.py
quantplay/broker/xts_utils_v2/__init__.py
quantplay/core/__init__.py
quantplay/core/strategy.py
quantplay/exception/__init__.py
quantplay/exception/exceptions.py
quantplay/indicator/__init__.py
quantplay/indicator/iv.py
quantplay/model/__init__.py
quantplay/model/broker.py
quantplay/model/broker_response.py
quantplay/model/generics.py
quantplay/model/instrument_data.py
quantplay/model/order_event.py
quantplay-2.1.97.dist-info/METADATA
quantplay-2.1.97.dist-info/WHEEL
quantplay-2.1.97.dist-info/top_level.txt
quantplay-2.1.97.dist-info/RECORD
